{"title":"go语言变量作用域","uid":"52d57ca0884fcc119dcf3941a54c9365","slug":"go语言变量作用域","date":"2023-11-22T19:30:46.526Z","updated":"2023-11-22T19:30:46.527Z","comments":true,"path":"api/articles/go语言变量作用域.json","keywords":null,"cover":"/img/6.jpg","content":"<blockquote><span class=\"custom-blockquote-svg\"><svg width=\"24\" height=\"24\" viewBox=\"0 0 24 24\" fill=\"\" xmlns=\"http://www.w3.org/2000/svg\" data-reactroot=\"\">\n<path fill=\"\" d=\"M22 12C22 6.5 17.5 2 12 2C6.5 2 2 6.5 2 12C2 17.5 6.5 22 12 22C13.8 22 15.5 21.5 17 20.6L22 22L20.7 17C21.5 15.5 22 13.8 22 12Z\" undefined=\"1\"></path>\n<path fill=\"\" d=\"M15.97 11.5H16.04C17.12 11.5 18 12.38 18 13.47V13.53C18 14.62 17.12 15.5 16.03 15.5H15.96C14.88 15.5 14 14.62 14 13.53V13.46C14 12.38 14.88 11.5 15.97 11.5Z\" undefined=\"1\"></path>\n<path fill=\"\" d=\"M7.97 11.5H8.04C9.12 11.5 10 12.38 10 13.47V13.53C10 14.62 9.12 15.5 8.03 15.5H7.97C6.88 15.5 6 14.62 6 13.53V13.46C6 12.38 6.88 11.5 7.97 11.5Z\" undefined=\"1\"></path>\n<path stroke-linejoin=\"round\" stroke-linecap=\"round\" stroke-miterlimit=\"10\" stroke-width=\"2\" stroke=\"\" d=\"M17 8.5C15.23 8.97 14.07 10.84 14.01 13.27C14 13.33 14 13.4 14 13.47V13.5\"></path>\n<path stroke-linejoin=\"round\" stroke-linecap=\"round\" stroke-miterlimit=\"10\" stroke-width=\"2\" stroke=\"\" d=\"M9 8.5C7.23 8.97 6.07 10.84 6.01 13.27C6 13.33 6 13.4 6 13.47V13.5\"></path>\n<path stroke-linejoin=\"round\" stroke-linecap=\"round\" stroke-miterlimit=\"10\" stroke-width=\"2\" stroke=\"\" d=\"M15.97 11.5H16.04C17.12 11.5 18 12.38 18 13.47V13.53C18 14.62 17.12 15.5 16.03 15.5H15.96C14.88 15.5 14 14.62 14 13.53V13.46C14 12.38 14.88 11.5 15.97 11.5Z\"></path>\n<path stroke-linejoin=\"round\" stroke-linecap=\"round\" stroke-miterlimit=\"10\" stroke-width=\"2\" stroke=\"\" d=\"M7.97 11.5H8.04C9.12 11.5 10 12.38 10 13.47V13.53C10 14.62 9.12 15.5 8.03 15.5H7.97C6.88 15.5 6 14.62 6 13.53V13.46C6 12.38 6.88 11.5 7.97 11.5Z\"></path>\n</svg>\n</span><p>作用域为已声明标识符所表示的常量、类型、变量、函数或包在源代码中的作用范围。<br>Go 语言中变量可以在三个地方声明：<br>函数内定义的变量称为局部变量<br>函数外定义的变量称为全局变量<br>函数定义中的变量称为形式参数</p></blockquote>\n<h1 id=\"局部变量\"><a href=\"#局部变量\" class=\"headerlink\" title=\"局部变量\"></a>局部变量</h1><blockquote><span class=\"custom-blockquote-svg\"><svg width=\"24\" height=\"24\" viewBox=\"0 0 24 24\" fill=\"\" xmlns=\"http://www.w3.org/2000/svg\" data-reactroot=\"\">\n<path fill=\"\" d=\"M22 12C22 6.5 17.5 2 12 2C6.5 2 2 6.5 2 12C2 17.5 6.5 22 12 22C13.8 22 15.5 21.5 17 20.6L22 22L20.7 17C21.5 15.5 22 13.8 22 12Z\" undefined=\"1\"></path>\n<path fill=\"\" d=\"M15.97 11.5H16.04C17.12 11.5 18 12.38 18 13.47V13.53C18 14.62 17.12 15.5 16.03 15.5H15.96C14.88 15.5 14 14.62 14 13.53V13.46C14 12.38 14.88 11.5 15.97 11.5Z\" undefined=\"1\"></path>\n<path fill=\"\" d=\"M7.97 11.5H8.04C9.12 11.5 10 12.38 10 13.47V13.53C10 14.62 9.12 15.5 8.03 15.5H7.97C6.88 15.5 6 14.62 6 13.53V13.46C6 12.38 6.88 11.5 7.97 11.5Z\" undefined=\"1\"></path>\n<path stroke-linejoin=\"round\" stroke-linecap=\"round\" stroke-miterlimit=\"10\" stroke-width=\"2\" stroke=\"\" d=\"M17 8.5C15.23 8.97 14.07 10.84 14.01 13.27C14 13.33 14 13.4 14 13.47V13.5\"></path>\n<path stroke-linejoin=\"round\" stroke-linecap=\"round\" stroke-miterlimit=\"10\" stroke-width=\"2\" stroke=\"\" d=\"M9 8.5C7.23 8.97 6.07 10.84 6.01 13.27C6 13.33 6 13.4 6 13.47V13.5\"></path>\n<path stroke-linejoin=\"round\" stroke-linecap=\"round\" stroke-miterlimit=\"10\" stroke-width=\"2\" stroke=\"\" d=\"M15.97 11.5H16.04C17.12 11.5 18 12.38 18 13.47V13.53C18 14.62 17.12 15.5 16.03 15.5H15.96C14.88 15.5 14 14.62 14 13.53V13.46C14 12.38 14.88 11.5 15.97 11.5Z\"></path>\n<path stroke-linejoin=\"round\" stroke-linecap=\"round\" stroke-miterlimit=\"10\" stroke-width=\"2\" stroke=\"\" d=\"M7.97 11.5H8.04C9.12 11.5 10 12.38 10 13.47V13.53C10 14.62 9.12 15.5 8.03 15.5H7.97C6.88 15.5 6 14.62 6 13.53V13.46C6 12.38 6.88 11.5 7.97 11.5Z\"></path>\n</svg>\n</span><p>在函数体内声明的变量称之为局部变量，它们的作用域只在函数体内，参数和返回值变量也是局部变量。</p></blockquote>\n<p>因为之前也用过，因此不过多叙述，接下来用简单的代码展示一下局部变量</p>\n<figure class=\"highlight plaintext\"><table><tr><td class=\"gutter\"><pre><span class=\"line\">1</span><br><span class=\"line\">2</span><br><span class=\"line\">3</span><br><span class=\"line\">4</span><br><span class=\"line\">5</span><br><span class=\"line\">6</span><br><span class=\"line\">7</span><br><span class=\"line\">8</span><br><span class=\"line\">9</span><br><span class=\"line\">10</span><br><span class=\"line\">11</span><br><span class=\"line\">12</span><br><span class=\"line\">13</span><br></pre></td><td class=\"code\"><pre><span class=\"line\">package main</span><br><span class=\"line\"></span><br><span class=\"line\">import &quot;fmt&quot;</span><br><span class=\"line\"></span><br><span class=\"line\">func main() &#123;</span><br><span class=\"line\">    var a, b, c int</span><br><span class=\"line\"></span><br><span class=\"line\">    a = 10</span><br><span class=\"line\">    b = 20</span><br><span class=\"line\">    c = a + b</span><br><span class=\"line\"></span><br><span class=\"line\">    fmt.Printf(&quot;结果： a = %d, b = %d and c = %d\\n&quot;, a, b, c)</span><br><span class=\"line\">&#125;</span><br></pre></td></tr></table></figure>\n\n<p>输出：<br><img src=\"https://nnnpc-1311441040.cos.ap-shanghai.myqcloud.com/gY0j2etnawVMnPhP.png!thumbnail\" title=\"fig:\"></p>\n<p>如上述代码，abc三个变量在main函数中被声明，也就是abc的作用域在main函数当中，外部无法不声明直接引用这三个变量</p>\n<h1 id=\"全局变量\"><a href=\"#全局变量\" class=\"headerlink\" title=\"全局变量\"></a>全局变量</h1><blockquote><span class=\"custom-blockquote-svg\"><svg width=\"24\" height=\"24\" viewBox=\"0 0 24 24\" fill=\"\" xmlns=\"http://www.w3.org/2000/svg\" data-reactroot=\"\">\n<path fill=\"\" d=\"M22 12C22 6.5 17.5 2 12 2C6.5 2 2 6.5 2 12C2 17.5 6.5 22 12 22C13.8 22 15.5 21.5 17 20.6L22 22L20.7 17C21.5 15.5 22 13.8 22 12Z\" undefined=\"1\"></path>\n<path fill=\"\" d=\"M15.97 11.5H16.04C17.12 11.5 18 12.38 18 13.47V13.53C18 14.62 17.12 15.5 16.03 15.5H15.96C14.88 15.5 14 14.62 14 13.53V13.46C14 12.38 14.88 11.5 15.97 11.5Z\" undefined=\"1\"></path>\n<path fill=\"\" d=\"M7.97 11.5H8.04C9.12 11.5 10 12.38 10 13.47V13.53C10 14.62 9.12 15.5 8.03 15.5H7.97C6.88 15.5 6 14.62 6 13.53V13.46C6 12.38 6.88 11.5 7.97 11.5Z\" undefined=\"1\"></path>\n<path stroke-linejoin=\"round\" stroke-linecap=\"round\" stroke-miterlimit=\"10\" stroke-width=\"2\" stroke=\"\" d=\"M17 8.5C15.23 8.97 14.07 10.84 14.01 13.27C14 13.33 14 13.4 14 13.47V13.5\"></path>\n<path stroke-linejoin=\"round\" stroke-linecap=\"round\" stroke-miterlimit=\"10\" stroke-width=\"2\" stroke=\"\" d=\"M9 8.5C7.23 8.97 6.07 10.84 6.01 13.27C6 13.33 6 13.4 6 13.47V13.5\"></path>\n<path stroke-linejoin=\"round\" stroke-linecap=\"round\" stroke-miterlimit=\"10\" stroke-width=\"2\" stroke=\"\" d=\"M15.97 11.5H16.04C17.12 11.5 18 12.38 18 13.47V13.53C18 14.62 17.12 15.5 16.03 15.5H15.96C14.88 15.5 14 14.62 14 13.53V13.46C14 12.38 14.88 11.5 15.97 11.5Z\"></path>\n<path stroke-linejoin=\"round\" stroke-linecap=\"round\" stroke-miterlimit=\"10\" stroke-width=\"2\" stroke=\"\" d=\"M7.97 11.5H8.04C9.12 11.5 10 12.38 10 13.47V13.53C10 14.62 9.12 15.5 8.03 15.5H7.97C6.88 15.5 6 14.62 6 13.53V13.46C6 12.38 6.88 11.5 7.97 11.5Z\"></path>\n</svg>\n</span><p>在函数体外声明的变量称之为全局变量，全局变量可以在整个包甚至外部包（被导出后）使用。</p></blockquote>\n<p>全局变量之所以被称为全局，也就是在整一个程序中都可以被引用。因此在函数体外进行声明，在任何函数当中都可以使用</p>\n<figure class=\"highlight plaintext\"><table><tr><td class=\"gutter\"><pre><span class=\"line\">1</span><br><span class=\"line\">2</span><br><span class=\"line\">3</span><br><span class=\"line\">4</span><br><span class=\"line\">5</span><br><span class=\"line\">6</span><br><span class=\"line\">7</span><br><span class=\"line\">8</span><br><span class=\"line\">9</span><br><span class=\"line\">10</span><br><span class=\"line\">11</span><br><span class=\"line\">12</span><br><span class=\"line\">13</span><br><span class=\"line\">14</span><br><span class=\"line\">15</span><br><span class=\"line\">16</span><br></pre></td><td class=\"code\"><pre><span class=\"line\">package main</span><br><span class=\"line\"></span><br><span class=\"line\">import &quot;fmt&quot;</span><br><span class=\"line\"></span><br><span class=\"line\">var g int</span><br><span class=\"line\"></span><br><span class=\"line\">func main() &#123;</span><br><span class=\"line\"></span><br><span class=\"line\">    var a, b int</span><br><span class=\"line\"></span><br><span class=\"line\">    a = 10</span><br><span class=\"line\">    b = 20</span><br><span class=\"line\">    g = a + b</span><br><span class=\"line\"></span><br><span class=\"line\">    fmt.Printf(&quot;结果： a = %d, b = %d and g = %d\\n&quot;, a, b, g)</span><br><span class=\"line\">&#125;</span><br></pre></td></tr></table></figure>\n\n<p>输出：<br><img src=\"https://nnnpc-1311441040.cos.ap-shanghai.myqcloud.com/BRUfNatomzmI98nb.png!thumbnail\" title=\"fig:\"></p>\n<p>如上述程序可以知道，ab依然为main函数中声明的局部变量，只能在main函数中使用，但g在函数外进行声明，因此g为全局变量，main函数中也可以使用</p>\n<p>这时候可以就会想到一个问题，全局变量和局部变量的变量名相同时会不会引起冲突呢？答案是并不会，但在函数体当中，会优先考虑该函数体中声明的全局变量，如下实例：</p>\n<figure class=\"highlight plaintext\"><table><tr><td class=\"gutter\"><pre><span class=\"line\">1</span><br><span class=\"line\">2</span><br><span class=\"line\">3</span><br><span class=\"line\">4</span><br><span class=\"line\">5</span><br><span class=\"line\">6</span><br><span class=\"line\">7</span><br><span class=\"line\">8</span><br><span class=\"line\">9</span><br><span class=\"line\">10</span><br><span class=\"line\">11</span><br><span class=\"line\">12</span><br></pre></td><td class=\"code\"><pre><span class=\"line\">package main</span><br><span class=\"line\"></span><br><span class=\"line\">import &quot;fmt&quot;</span><br><span class=\"line\"></span><br><span class=\"line\">var g int = 20</span><br><span class=\"line\"></span><br><span class=\"line\">func main() &#123;</span><br><span class=\"line\"></span><br><span class=\"line\">    var g int = 10</span><br><span class=\"line\">    fmt.Printf(&quot;结果： g = %d\\n&quot;, g)</span><br><span class=\"line\"></span><br><span class=\"line\">&#125;</span><br></pre></td></tr></table></figure>\n\n<p>输出：<br><img src=\"https://nnnpc-1311441040.cos.ap-shanghai.myqcloud.com/o5UWbCRCElJXUFHN.png!thumbnail\" title=\"fig:\"></p>\n<p>可以看到变量名同为g时，main函数中的优先输出是局部变量的g值</p>\n<h1 id=\"形式参数\"><a href=\"#形式参数\" class=\"headerlink\" title=\"形式参数\"></a>形式参数</h1><blockquote><span class=\"custom-blockquote-svg\"><svg width=\"24\" height=\"24\" viewBox=\"0 0 24 24\" fill=\"\" xmlns=\"http://www.w3.org/2000/svg\" data-reactroot=\"\">\n<path fill=\"\" d=\"M22 12C22 6.5 17.5 2 12 2C6.5 2 2 6.5 2 12C2 17.5 6.5 22 12 22C13.8 22 15.5 21.5 17 20.6L22 22L20.7 17C21.5 15.5 22 13.8 22 12Z\" undefined=\"1\"></path>\n<path fill=\"\" d=\"M15.97 11.5H16.04C17.12 11.5 18 12.38 18 13.47V13.53C18 14.62 17.12 15.5 16.03 15.5H15.96C14.88 15.5 14 14.62 14 13.53V13.46C14 12.38 14.88 11.5 15.97 11.5Z\" undefined=\"1\"></path>\n<path fill=\"\" d=\"M7.97 11.5H8.04C9.12 11.5 10 12.38 10 13.47V13.53C10 14.62 9.12 15.5 8.03 15.5H7.97C6.88 15.5 6 14.62 6 13.53V13.46C6 12.38 6.88 11.5 7.97 11.5Z\" undefined=\"1\"></path>\n<path stroke-linejoin=\"round\" stroke-linecap=\"round\" stroke-miterlimit=\"10\" stroke-width=\"2\" stroke=\"\" d=\"M17 8.5C15.23 8.97 14.07 10.84 14.01 13.27C14 13.33 14 13.4 14 13.47V13.5\"></path>\n<path stroke-linejoin=\"round\" stroke-linecap=\"round\" stroke-miterlimit=\"10\" stroke-width=\"2\" stroke=\"\" d=\"M9 8.5C7.23 8.97 6.07 10.84 6.01 13.27C6 13.33 6 13.4 6 13.47V13.5\"></path>\n<path stroke-linejoin=\"round\" stroke-linecap=\"round\" stroke-miterlimit=\"10\" stroke-width=\"2\" stroke=\"\" d=\"M15.97 11.5H16.04C17.12 11.5 18 12.38 18 13.47V13.53C18 14.62 17.12 15.5 16.03 15.5H15.96C14.88 15.5 14 14.62 14 13.53V13.46C14 12.38 14.88 11.5 15.97 11.5Z\"></path>\n<path stroke-linejoin=\"round\" stroke-linecap=\"round\" stroke-miterlimit=\"10\" stroke-width=\"2\" stroke=\"\" d=\"M7.97 11.5H8.04C9.12 11.5 10 12.38 10 13.47V13.53C10 14.62 9.12 15.5 8.03 15.5H7.97C6.88 15.5 6 14.62 6 13.53V13.46C6 12.38 6.88 11.5 7.97 11.5Z\"></path>\n</svg>\n</span><p>形式参数会作为函数的局部变量来使用</p></blockquote>\n<figure class=\"highlight plaintext\"><table><tr><td class=\"gutter\"><pre><span class=\"line\">1</span><br><span class=\"line\">2</span><br><span class=\"line\">3</span><br><span class=\"line\">4</span><br><span class=\"line\">5</span><br><span class=\"line\">6</span><br><span class=\"line\">7</span><br><span class=\"line\">8</span><br><span class=\"line\">9</span><br><span class=\"line\">10</span><br><span class=\"line\">11</span><br><span class=\"line\">12</span><br><span class=\"line\">13</span><br><span class=\"line\">14</span><br><span class=\"line\">15</span><br><span class=\"line\">16</span><br><span class=\"line\">17</span><br><span class=\"line\">18</span><br><span class=\"line\">19</span><br><span class=\"line\">20</span><br><span class=\"line\">21</span><br><span class=\"line\">22</span><br></pre></td><td class=\"code\"><pre><span class=\"line\">package main</span><br><span class=\"line\"></span><br><span class=\"line\">import &quot;fmt&quot;</span><br><span class=\"line\"></span><br><span class=\"line\">var a int = 20</span><br><span class=\"line\"></span><br><span class=\"line\">func main() &#123;</span><br><span class=\"line\">    var a int = 10</span><br><span class=\"line\">    var b int = 20</span><br><span class=\"line\">    var c int = 0</span><br><span class=\"line\"></span><br><span class=\"line\">    fmt.Printf(&quot;main()函数中 a = %d\\n&quot;, a)</span><br><span class=\"line\">    c = sum(a, b)</span><br><span class=\"line\">    fmt.Printf(&quot;main()函数中 c = %d\\n&quot;, c)</span><br><span class=\"line\">&#125;</span><br><span class=\"line\"></span><br><span class=\"line\">func sum(a, b int) int &#123;</span><br><span class=\"line\">    fmt.Printf(&quot;sum() 函数中 a = %d\\n&quot;, a)</span><br><span class=\"line\">    fmt.Printf(&quot;sum() 函数中 b = %d\\n&quot;, b)</span><br><span class=\"line\"></span><br><span class=\"line\">    return a + b</span><br><span class=\"line\">&#125;</span><br></pre></td></tr></table></figure>\n\n<p>输出：<br><img src=\"https://nnnpc-1311441040.cos.ap-shanghai.myqcloud.com/qDL0KThcBshap6IG.png!thumbnail\" title=\"fig:\"></p>\n<p>分别来解释一下输出和作用域，在两个函数之外的a毋庸置疑是全局变量，作用域在全局，但是main函数中也声明了变量a，因此优先级高于全局的，输出为10<br>。接着调用了sum函数，而在sum函数定义了a，b两个形参，作为局部变量，因此作用域仅在sum函数中，在接收到main函数中a，b的值传递后，输出的a，b值也就是main函数中a，b的值，为10和20<br>。将返回的a+b值赋给了c，因此main函数中输出的c值为30</p>\n<p>当函数中没有进行重新声明赋值时，默认使用全局变量</p>\n<figure class=\"highlight plaintext\"><table><tr><td class=\"gutter\"><pre><span class=\"line\">1</span><br><span class=\"line\">2</span><br><span class=\"line\">3</span><br><span class=\"line\">4</span><br><span class=\"line\">5</span><br><span class=\"line\">6</span><br><span class=\"line\">7</span><br><span class=\"line\">8</span><br><span class=\"line\">9</span><br><span class=\"line\">10</span><br><span class=\"line\">11</span><br><span class=\"line\">12</span><br><span class=\"line\">13</span><br><span class=\"line\">14</span><br><span class=\"line\">15</span><br><span class=\"line\">16</span><br><span class=\"line\">17</span><br><span class=\"line\">18</span><br><span class=\"line\">19</span><br><span class=\"line\">20</span><br></pre></td><td class=\"code\"><pre><span class=\"line\">package main</span><br><span class=\"line\"></span><br><span class=\"line\">import &quot;fmt&quot;</span><br><span class=\"line\"></span><br><span class=\"line\">var a int = 20</span><br><span class=\"line\">var b int = 20</span><br><span class=\"line\"></span><br><span class=\"line\">func main() &#123;</span><br><span class=\"line\">    var c = 0</span><br><span class=\"line\">    c = sum(a, b)</span><br><span class=\"line\">    fmt.Printf(&quot;main() 函数中 c = %d\\n&quot;, c)</span><br><span class=\"line\"></span><br><span class=\"line\">&#125;</span><br><span class=\"line\"></span><br><span class=\"line\">func sum(a, b int) int &#123;</span><br><span class=\"line\">    fmt.Printf(&quot;sum() 函数中 a = %d\\n&quot;, a)</span><br><span class=\"line\">    fmt.Printf(&quot;sum() 函数中 b = %d\\n&quot;, b)</span><br><span class=\"line\"></span><br><span class=\"line\">    return a + b</span><br><span class=\"line\">&#125;</span><br></pre></td></tr></table></figure>\n\n<p>输出：<br><img src=\"https://nnnpc-1311441040.cos.ap-shanghai.myqcloud.com/fdkdqXXyXfdkcyGP.png!thumbnail\" title=\"fig:\"></p>\n<h1 id=\"初始化局部和全局变量\"><a href=\"#初始化局部和全局变量\" class=\"headerlink\" title=\"初始化局部和全局变量\"></a>初始化局部和全局变量</h1><p>不同类型的局部和全局变量默认值为：</p>\n<p>  数据类型   初始化默认值</p>\n<hr>\n<p>  int        0<br>  float32    0<br>  pointer    nil</p>\n","feature":true,"text":" 作用域为已声明标识符所表示的常量、类型、变量、函数或包在源代码中的作用范围。Go 语言中变量可以在三个地方声明：函数内定义的变量称为局部变量函数外定义的变量称...","permalink":"/post/go语言变量作用域","photos":[],"count_time":{"symbolsCount":"2.3k","symbolsTime":"2 mins."},"categories":[{"name":"GO","slug":"GO","count":7,"path":"api/categories/GO.json"}],"tags":[{"name":"GO","slug":"GO","count":7,"path":"api/tags/GO.json"}],"toc":"<ol class=\"toc\"><li class=\"toc-item toc-level-1\"><a class=\"toc-link\" href=\"#%E5%B1%80%E9%83%A8%E5%8F%98%E9%87%8F\"><span class=\"toc-text\">局部变量</span></a></li><li class=\"toc-item toc-level-1\"><a class=\"toc-link\" href=\"#%E5%85%A8%E5%B1%80%E5%8F%98%E9%87%8F\"><span class=\"toc-text\">全局变量</span></a></li><li class=\"toc-item toc-level-1\"><a class=\"toc-link\" href=\"#%E5%BD%A2%E5%BC%8F%E5%8F%82%E6%95%B0\"><span class=\"toc-text\">形式参数</span></a></li><li class=\"toc-item toc-level-1\"><a class=\"toc-link\" href=\"#%E5%88%9D%E5%A7%8B%E5%8C%96%E5%B1%80%E9%83%A8%E5%92%8C%E5%85%A8%E5%B1%80%E5%8F%98%E9%87%8F\"><span class=\"toc-text\">初始化局部和全局变量</span></a></li></ol>","author":{"name":"nnnpc","slug":"blog-author","avatar":"/img/2.jpg","link":"/","description":"安全萌新","socials":{"github":"","twitter":"","stackoverflow":"","wechat":"","qq":"","weibo":"","zhihu":"","csdn":"","juejin":"","customs":{}}},"mapped":true,"hidden":false,"prev_post":{"title":"go条件语句","uid":"5d5c24dadfa81f93561fe4860d749b83","slug":"go条件语句","date":"2023-11-22T19:31:38.304Z","updated":"2023-11-22T19:31:38.306Z","comments":true,"path":"api/articles/go条件语句.json","keywords":null,"cover":"/img/6.jpg","text":" 条件语句需要开发者通过指定一个或多个条件，并通过测试条件是否为 true来决定是否执行指定语句，并在条件为 false 的情况在执行另外的语句。 语句 描述 ...","permalink":"/post/go条件语句","photos":[],"count_time":{"symbolsCount":"7.5k","symbolsTime":"7 mins."},"categories":[{"name":"GO","slug":"GO","count":7,"path":"api/categories/GO.json"}],"tags":[{"name":"GO","slug":"GO","count":7,"path":"api/tags/GO.json"}],"author":{"name":"nnnpc","slug":"blog-author","avatar":"/img/2.jpg","link":"/","description":"安全萌新","socials":{"github":"","twitter":"","stackoverflow":"","wechat":"","qq":"","weibo":"","zhihu":"","csdn":"","juejin":"","customs":{}}},"feature":true},"next_post":{"title":"go语言函数","uid":"14f39d25edcfe947fd2b26042086ecb4","slug":"go语言函数","date":"2023-11-22T19:29:29.379Z","updated":"2023-11-22T19:29:29.381Z","comments":true,"path":"api/articles/go语言函数.json","keywords":null,"cover":"/img/6.jpg","text":" 函数是基本的代码块，用于执行一个任务。Go 语言最少有个 main() 函数。你可以通过函数来划分不同功能，逻辑上每个函数执行的是指定的任务。函数声明告诉了编...","permalink":"/post/go语言函数","photos":[],"count_time":{"symbolsCount":568,"symbolsTime":"1 mins."},"categories":[{"name":"GO","slug":"GO","count":7,"path":"api/categories/GO.json"}],"tags":[{"name":"GO","slug":"GO","count":7,"path":"api/tags/GO.json"}],"author":{"name":"nnnpc","slug":"blog-author","avatar":"/img/2.jpg","link":"/","description":"安全萌新","socials":{"github":"","twitter":"","stackoverflow":"","wechat":"","qq":"","weibo":"","zhihu":"","csdn":"","juejin":"","customs":{}}}}}