{"title":"关于TCP与UDP协议的学习","uid":"18c38f78a2d6eaab55692fed5528365d","slug":"关于TCP与UDP协议的学习","date":"2023-11-23T08:20:02.223Z","updated":"2023-11-23T08:20:02.224Z","comments":true,"path":"api/articles/关于TCP与UDP协议的学习.json","keywords":null,"cover":"/img/6.jpg","content":"<p>TCP协议的三次握手，传输确认，四次挥手</p>\n<hr>\n<h2 id=\"一-TCP三次握手\"><a href=\"#一-TCP三次握手\" class=\"headerlink\" title=\"一.TCP三次握手\"></a>一.TCP三次握手</h2>","text":"TCP协议的三次握手，传输确认，四次挥手 一.TCP三次握手","permalink":"/post/关于TCP与UDP协议的学习","photos":[],"count_time":{"symbolsCount":31,"symbolsTime":"1 mins."},"categories":[{"name":"其它","slug":"其它","count":4,"path":"api/categories/其它.json"}],"tags":[{"name":"其它","slug":"其它","count":4,"path":"api/tags/其它.json"}],"toc":"<ol class=\"toc\"><li class=\"toc-item toc-level-2\"><a class=\"toc-link\" href=\"#%E4%B8%80-TCP%E4%B8%89%E6%AC%A1%E6%8F%A1%E6%89%8B\"><span class=\"toc-text\">一.TCP三次握手</span></a></li></ol>","author":{"name":"nnnpc","slug":"blog-author","avatar":"/img/2.jpg","link":"/","description":"安全萌新","socials":{"github":"","twitter":"","stackoverflow":"","wechat":"","qq":"","weibo":"","zhihu":"","csdn":"","juejin":"","customs":{}}},"mapped":true,"hidden":false,"prev_post":{"title":"CTFshow文件包含","uid":"2c7fab40a3af62d04adc78f0d5f8c9ed","slug":"CTFshow文件包含","date":"2023-11-23T08:34:49.059Z","updated":"2023-11-23T08:34:49.061Z","comments":true,"path":"api/articles/CTFshow文件包含.json","keywords":null,"cover":"/img/6.jpg","text":"初学文件包含刚开始只懂一些伪协议什么的，对于一个具体的文件包含并不是很了解，先简单记录下原理 文件包含漏洞:通过PHP函数引入文件时，传入的文件名没有经过合理的...","permalink":"/post/CTFshow文件包含","photos":[],"count_time":{"symbolsCount":"6.2k","symbolsTime":"6 mins."},"categories":[{"name":"WEB","slug":"WEB","count":5,"path":"api/categories/WEB.json"}],"tags":[{"name":"WEB","slug":"WEB","count":5,"path":"api/tags/WEB.json"}],"author":{"name":"nnnpc","slug":"blog-author","avatar":"/img/2.jpg","link":"/","description":"安全萌新","socials":{"github":"","twitter":"","stackoverflow":"","wechat":"","qq":"","weibo":"","zhihu":"","csdn":"","juejin":"","customs":{}}}},"next_post":{"title":"可执行文件的转换","uid":"40028e766145a408fb22d4a74e20290f","slug":"可执行文件的转换","date":"2023-11-23T08:15:55.988Z","updated":"2023-11-23T08:15:55.989Z","comments":true,"path":"api/articles/可执行文件的转换.json","keywords":null,"cover":"/img/6.jpg","text":" 当开发者向普通用户分享程序时，为了方便用户在未安装Python环境的情况下能够正常运行，需要将开发好的程序进行打包，转换成用户可运行的文件类型。PyInsta...","permalink":"/post/可执行文件的转换","photos":[],"count_time":{"symbolsCount":"1.2k","symbolsTime":"1 mins."},"categories":[{"name":"python","slug":"python","count":15,"path":"api/categories/python.json"}],"tags":[{"name":"python","slug":"python","count":15,"path":"api/tags/python.json"}],"author":{"name":"nnnpc","slug":"blog-author","avatar":"/img/2.jpg","link":"/","description":"安全萌新","socials":{"github":"","twitter":"","stackoverflow":"","wechat":"","qq":"","weibo":"","zhihu":"","csdn":"","juejin":"","customs":{}}}}}